LICENSE.txt
MANIFEST.in
README.md
pyproject.toml
settings.ini
setup.py
docs/CodeStatus.md
docs/examples.md
pylevis/Mercury.py
pylevis/__init__.py
pylevis/constants.py
pylevis/directories.py
pylevis.egg-info/PKG-INFO
pylevis.egg-info/SOURCES.txt
pylevis.egg-info/dependency_links.txt
pylevis.egg-info/requires.txt
pylevis.egg-info/top_level.txt
pylevis/equilibrium/Get_FieldLine.py
pylevis/equilibrium/__init__.py
pylevis/io/Get_BackgroundProfiles.py
pylevis/io/Get_BackupEquilibrium.py
pylevis/io/Get_Collisions.py
pylevis/io/Get_Diffusivity.py
pylevis/io/Get_EnergyData.py
pylevis/io/Get_Equilibrium.py
pylevis/io/Get_FieldsData.py
pylevis/io/Get_InitialParams.py
pylevis/io/Get_Moments.py
pylevis/io/Get_PlasmaVolume.py
pylevis/io/__init__.py
pylevis/newsimulation/Init_ParticleDistribution.py
pylevis/newsimulation/Init_Simulation.py
pylevis/newsimulation/Init_visualise.py
pylevis/newsimulation/__init__.py
pylevis/newsimulation/class_data.py
pylevis/particles/Get_InitialParticleData.py
pylevis/particles/ParticleClass.py
pylevis/particles/__init__.py
pylevis/particles/ext_fns.py
pylevis/visualisation/__init__.py
pylevis/visualisation/plots_moments.py
pylevis/visualisation/plots_single_particle.py
pylevis/visualisation/plottingfns.py
pylevis/visualisation/support.py