Metadata-Version: 2.1
Name: pylevis
Version: 0.216
Summary: Python utilities/interface for VENUS-LEVIS fast particle orbit code
Home-page: https://github.com/Spiffmeister/pyLEVIS
Author: Dean Muir
License: GNU 3.0
Platform: UNKNOWN
Classifier: Programming Language :: Python :: 3
Classifier: License :: OSI Approved :: GNU Lesser General Public License v3 or later (LGPLv3+)
Classifier: Topic :: Scientific/Engineering
Requires-Python: >=3.6
